wagtailtables/__init__.py
wagtailtables/apps.py
wagtailtables/blocks.py
wagtailtables/static/wagtailtables/css/jspreadsheet.css
wagtailtables/static/wagtailtables/css/jspreadsheet.theme.css
wagtailtables/static/wagtailtables/css/jsuites.css
wagtailtables/static/wagtailtables/js/jspreadsheet.js
wagtailtables/static/wagtailtables/js/jsuites.js
wagtailtables/static/wagtailtables/js/table-dataset.js
wagtailtables/templates/wagtailtables/table_block.html
wagtailtables/templatetags/__init__.py
wagtailtables/templatetags/wagtailtables_tags.py
wagtailtables-0.2.2.dist-info/LICENSE.txt
wagtailtables-0.2.2.dist-info/METADATA
wagtailtables-0.2.2.dist-info/WHEEL
wagtailtables-0.2.2.dist-info/top_level.txt
wagtailtables-0.2.2.dist-info/RECORD
