Metadata-Version: 2.1
Name: wagtailtables
Version: 0.2.2
Summary: jSpreadsheet table blocks for Wagtail
Home-page: https://github.com/overcast/wagtailtables/
Author: Overcast
Author-email: hallo@overcast.is
License: MIT
Classifier: Environment :: Web Environment
Classifier: Framework :: Django
Classifier: Framework :: Wagtail
Classifier: Framework :: Wagtail :: 3
Classifier: Framework :: Wagtail :: 4
Classifier: Framework :: Wagtail :: 5
Classifier: Intended Audience :: Developers
Classifier: License :: OSI Approved :: MIT License
Classifier: Operating System :: OS Independent
Classifier: Programming Language :: Python
Classifier: Programming Language :: Python :: 3
Classifier: Programming Language :: Python :: 3.10
Classifier: Programming Language :: Python :: 3.11
Classifier: Topic :: Internet :: WWW/HTTP
Classifier: Topic :: Internet :: WWW/HTTP :: Dynamic Content
License-File: LICENSE.txt
Requires-Dist: wagtail >=3.0
Provides-Extra: docs
Provides-Extra: testing
